{
  "mode": "light",
  "light": {
    "primaryColor": "#2563eb",
    "secondaryColor": "#0ea5e9",
    "accentColor": "#22c55e",
    "backgroundColor": "#ffffff",
    "foregroundColor": "#111827",
    "borderColor": "#e5e7eb",
    "panelColor": "#ffffff",
    "linkColor": "#2563eb",
    "mutedBgColor": "#f9fafb",
    "mutedTextColor": "#1b1c1d",
    "successColor": "#16a34a",
    "warningColor": "#f59e0b",
    "errorColor": "#dc2626",
    "fontFamily": "Inter, system-ui, -apple-system, Segoe UI, Roboto, Ubuntu, Cantarell, Noto Sans, Helvetica Neue, Arial, \"Apple Color Emoji\", \"Segoe UI Emoji\"",
    "baseFontSize": "14px",
    "borderRadius": "0.5rem"
  },
  "dark": {
    "primaryColor": "#2563eb",
    "secondaryColor": "#0ea5e9",
    "accentColor": "#22c55e",
    "backgroundColor": "#ffffff",
    "foregroundColor": "#111827",
    "borderColor": "#e5e7eb",
    "panelColor": "#ffffff",
    "linkColor": "#2563eb",
    "mutedBgColor": "#f9fafb",
    "mutedTextColor": "#6b7280",
    "successColor": "#16a34a",
    "warningColor": "#f59e0b",
    "errorColor": "#dc2626",
    "fontFamily": "Inter, system-ui, -apple-system, Segoe UI, Roboto, Ubuntu, Cantarell, Noto Sans, Helvetica Neue, Arial, \"Apple Color Emoji\", \"Segoe UI Emoji\"",
    "baseFontSize": "14px",
    "borderRadius": "0.5rem"
  },
  "fontProvider": "system",
  "googleFont": "Inter",
  "components": {
    "buttonStyle": "solid",
    "buttonTextCase": "normal",
    "inputBorderWidth": "1px",
    "focusRingColor": "#2563eb66",
    "tableStriped": true,
    "tableStripeColor": "#f5f7fb",
    "buttonRadius": "0.5rem",
    "buttonPaddingX": "0.75rem",
    "buttonPaddingY": "0.5rem",
    "inputRadius": "0.5rem",
    "inputPaddingX": "0.75rem",
    "inputPaddingY": "0.5rem"
  },
  "layout": {
    "contentMaxWidth": "1200px",
    "sidebarWidth": "16rem",
    "spacingUnit": "8px",
    "cardShadow": "sm"
  },
  "presets": {
    "default": {
      "mode": "light",
      "light": {
        "primaryColor": "#2563eb",
        "secondaryColor": "#0ea5e9",
        "accentColor": "#22c55e",
        "backgroundColor": "#ffffff",
        "foregroundColor": "#111827",
        "borderColor": "#e5e7eb",
        "panelColor": "#ffffff",
        "linkColor": "#2563eb",
        "mutedBgColor": "#f9fafb",
        "mutedTextColor": "#6b7280",
        "successColor": "#16a34a",
        "warningColor": "#f59e0b",
        "errorColor": "#dc2626",
        "fontFamily": "Inter, system-ui, -apple-system, Segoe UI, Roboto, Ubuntu, Cantarell, Noto Sans, Helvetica Neue, Arial, \"Apple Color Emoji\", \"Segoe UI Emoji\"",
        "baseFontSize": "14px",
        "borderRadius": "0.5rem"
      },
      "dark": {
        "primaryColor": "#2563eb",
        "secondaryColor": "#0ea5e9",
        "accentColor": "#22c55e",
        "backgroundColor": "#0b1220",
        "foregroundColor": "#e5e7eb",
        "borderColor": "#1f2937",
        "panelColor": "#0f172a",
        "linkColor": "#60a5fa",
        "mutedBgColor": "#111827",
        "mutedTextColor": "#9ca3af",
        "successColor": "#16a34a",
        "warningColor": "#f59e0b",
        "errorColor": "#dc2626",
        "fontFamily": "Inter, system-ui, -apple-system, Segoe UI, Roboto, Ubuntu, Cantarell, Noto Sans, Helvetica Neue, Arial, \"Apple Color Emoji\", \"Segoe UI Emoji\"",
        "baseFontSize": "14px",
        "borderRadius": "0.5rem"
      },
      "fontProvider": "system",
      "googleFont": "Inter"
    }
  }
}